README.md
setup.py
censius_explain/constants.py
censius_explain/explain.py
censius_explain/init.py
censius_explain.egg-info/PKG-INFO
censius_explain.egg-info/SOURCES.txt
censius_explain.egg-info/dependency_links.txt
censius_explain.egg-info/not-zip-safe
censius_explain.egg-info/requires.txt
censius_explain.egg-info/top_level.txt